bedrock/__init__.py
bedrock/backend.py
bedrock/blueprint.py
bedrock/cli.py
bedrock/config.py
bedrock/export.py
bedrock/terraform.py
bedrock/utils.py
tests/__init__.py
tests/test_backend.py
tests/test_blueprint.py
tests/test_config.py
tests/test_terraform.py
bedrockcli-1.0.7.dist-info/LICENSE
bedrockcli-1.0.7.dist-info/METADATA
bedrockcli-1.0.7.dist-info/WHEEL
bedrockcli-1.0.7.dist-info/entry_points.txt
bedrockcli-1.0.7.dist-info/top_level.txt
bedrockcli-1.0.7.dist-info/RECORD
