Metadata-Version: 2.1
Name: bedrockcli
Version: 1.0.7
Summary: A tool for managing Terraform blueprints
Home-page: https://github.com/micronode/bedrock-cli
Author: Ben Fortuna
Author-email: fortuna@micronode.com
License: UNKNOWN
Platform: UNKNOWN
Requires-Python: >=3.7
Requires-Dist: PyYAML (>=5.3.1)
Requires-Dist: docker (>=4.4.0)
Requires-Dist: dockerpty
Requires-Dist: simple-term-menu
